SaisiRangniChengweiMingyundeChuangzaozhe/Dockerfile
SaisiRangniChengweiMingyundeChuangzaozhe/README.md
SaisiRangniChengweiMingyundeChuangzaozhe/__init__.py
SaisiRangniChengweiMingyundeChuangzaozhe/__main__.py
SaisiRangniChengweiMingyundeChuangzaozhe/file.epub
SaisiRangniChengweiMingyundeChuangzaozhe/index.html
SaisiRangniChengweiMingyundeChuangzaozhe/css/__init__.py
SaisiRangniChengweiMingyundeChuangzaozhe/css/annotations.css
SaisiRangniChengweiMingyundeChuangzaozhe/css/main.css
SaisiRangniChengweiMingyundeChuangzaozhe/css/normalize.css
SaisiRangniChengweiMingyundeChuangzaozhe/css/popup.css
SaisiRangniChengweiMingyundeChuangzaozhe/font/__init__.py
SaisiRangniChengweiMingyundeChuangzaozhe/font/fontello.eot
SaisiRangniChengweiMingyundeChuangzaozhe/font/fontello.svg
SaisiRangniChengweiMingyundeChuangzaozhe/font/fontello.ttf
SaisiRangniChengweiMingyundeChuangzaozhe/font/fontello.woff
SaisiRangniChengweiMingyundeChuangzaozhe/img/__init__.py
SaisiRangniChengweiMingyundeChuangzaozhe/img/annotator-glyph-sprite.png
SaisiRangniChengweiMingyundeChuangzaozhe/img/annotator-icon-sprite.png
SaisiRangniChengweiMingyundeChuangzaozhe/img/apple-touch-icon.png
SaisiRangniChengweiMingyundeChuangzaozhe/img/cancelfullscreen.png
SaisiRangniChengweiMingyundeChuangzaozhe/img/close.png
SaisiRangniChengweiMingyundeChuangzaozhe/img/fullscreen.png
SaisiRangniChengweiMingyundeChuangzaozhe/img/loader.gif
SaisiRangniChengweiMingyundeChuangzaozhe/img/menu-icon.png
SaisiRangniChengweiMingyundeChuangzaozhe/img/save.png
SaisiRangniChengweiMingyundeChuangzaozhe/img/saved.png
SaisiRangniChengweiMingyundeChuangzaozhe/img/settings-s.png
SaisiRangniChengweiMingyundeChuangzaozhe/img/settings.png
SaisiRangniChengweiMingyundeChuangzaozhe/img/star.png
SaisiRangniChengweiMingyundeChuangzaozhe/js/__init__.py
SaisiRangniChengweiMingyundeChuangzaozhe/js/epub.js
SaisiRangniChengweiMingyundeChuangzaozhe/js/epub.min.js
SaisiRangniChengweiMingyundeChuangzaozhe/js/epub.min.map
saisi_rangni_chengwei_mingyunde_chuangzaozhe-2022.10.9.1.dist-info/METADATA
saisi_rangni_chengwei_mingyunde_chuangzaozhe-2022.10.9.1.dist-info/WHEEL
saisi_rangni_chengwei_mingyunde_chuangzaozhe-2022.10.9.1.dist-info/entry_points.txt
saisi_rangni_chengwei_mingyunde_chuangzaozhe-2022.10.9.1.dist-info/top_level.txt
saisi_rangni_chengwei_mingyunde_chuangzaozhe-2022.10.9.1.dist-info/RECORD
